setup.py
src/goephor/__init__.py
src/goephor/__main__.py
src/goephor/version.py
src/goephor.egg-info/PKG-INFO
src/goephor.egg-info/SOURCES.txt
src/goephor.egg-info/dependency_links.txt
src/goephor.egg-info/entry_points.txt
src/goephor.egg-info/not-zip-safe
src/goephor.egg-info/requires.txt
src/goephor.egg-info/top_level.txt
src/goephor/core/Chain.py
src/goephor/core/__init__.py
src/goephor/core/plugins/__init__.py
src/goephor/core/plugins/condition.py
src/goephor/core/plugins/environment.py
src/goephor/core/plugins/example.py
src/goephor/core/plugins/freebsd.py
src/goephor/core/plugins/handler.py
src/goephor/core/plugins/http.py
src/goephor/core/plugins/pluginable.py
src/goephor/core/plugins/receipt.py
src/goephor/core/plugins/release.py
src/goephor/core/plugins/remote.py
src/goephor/core/plugins/scm.py
src/goephor/core/plugins/string.py
src/goephor/core/plugins/system.py
src/goephor/core/plugins/modules/__init__.py
src/goephor/core/plugins/modules/action.py
src/goephor/core/plugins/modules/environment.py
src/goephor/core/plugins/modules/git_kit.py
src/goephor/core/plugins/modules/http.py
src/goephor/core/plugins/modules/log.py
src/goephor/core/plugins/modules/remote.py
src/goephor/core/plugins/modules/terminal.py