Metadata-Version: 1.1
Name: goephor
Version: 1.0.3
Summary: A build automation tool to drive processes described in a yaml manifest. Supported on [Freebsd, Linux, OSX] systems
Home-page: https://github.com/itow0001/goephor
Author: ian.itow
Author-email: itow0001@gmail.com
License: MIT
Platform: UNKNOWN
Classifier: Topic :: Software Development :: Build Tools
Classifier: Programming Language :: Python :: 2.7
